{"repo": "scala", "files": [{"status": "modified", "deletions": 32, "additions": 55, "changes": 87, "filename": "sources/ch/epfl/lamp/util/Position.java"}, {"status": "modified", "deletions": 51, "additions": 1, "changes": 52, "filename": "sources/ch/epfl/lamp/util/SourceFile.java"}, {"status": "modified", "deletions": 1, "additions": 1, "changes": 2, "filename": "sources/scala/tools/scalai/EvaluatorException.java"}, {"status": "modified", "deletions": 11, "additions": 8, "changes": 19, "filename": "sources/scalac/Unit.java"}, {"status": "modified", "deletions": 8, "additions": 4, "changes": 12, "filename": "sources/scalac/ast/parser/Scanner.java"}, {"status": "modified", "deletions": 1, "additions": 1, "changes": 2, "filename": "sources/scalac/backend/msil/GenMSIL.java"}, {"status": "modified", "deletions": 1, "additions": 1, "changes": 2, "filename": "sources/scalac/backend/msil/TypeCreator.java"}, {"status": "modified", "deletions": 7, "additions": 3, "changes": 10, "filename": "sources/scalac/util/Reporter.java"}], "stats": {"deletions": 112, "additions": 74, "total": 186}, "commit": {"date": "2003-06-24T08:57:30Z", "authorId": "", "author": "paltherr"}}