{"repo": "scala", "files": [{"status": "modified", "deletions": 0, "additions": 1, "changes": 1, "filename": "config/list/scalac.lst"}, {"status": "modified", "deletions": 2, "additions": 4, "changes": 6, "filename": "sources/scala/runtime/matching/Grammar.scala"}, {"status": "modified", "deletions": 62, "additions": 24, "changes": 86, "filename": "sources/scala/runtime/matching/Matcher.scala"}, {"status": "modified", "deletions": 1, "additions": 8, "changes": 9, "filename": "sources/scala/tools/scalac/transformer/TransMatch.scala"}, {"status": "modified", "deletions": 4, "additions": 11, "changes": 15, "filename": "sources/scala/tools/scalac/transformer/matching/FullRegularTranslator.scala"}, {"status": "modified", "deletions": 1, "additions": 3, "changes": 4, "filename": "sources/scala/tools/scalac/transformer/matching/MutableGrammar.scala"}, {"status": "modified", "deletions": 0, "additions": 1, "changes": 1, "filename": "sources/scala/xml/Text.scala"}, {"status": "modified", "deletions": 2, "additions": 4, "changes": 6, "filename": "sources/scala/xml/Utility.scala"}], "stats": {"deletions": 72, "additions": 56, "total": 128}, "commit": {"date": "2004-05-25T10:29:35Z", "authorId": "", "author": "buraq"}}