{"repo": "git", "files": [{"status": "modified", "deletions": 2, "additions": 9, "changes": 11, "filename": "Documentation/git-checkout.txt"}, {"status": "modified", "deletions": 1, "additions": 38, "changes": 39, "filename": "builtin-checkout.c"}, {"status": "modified", "deletions": 0, "additions": 25, "changes": 25, "filename": "t/t7201-co.sh"}], "stats": {"deletions": 3, "additions": 72, "total": 75}, "commit": {"date": "2008-08-30T14:48:18Z", "authorId": "gitster", "author": "Junio C Hamano"}}