{"repo": "mysql", "files": [{"status": "modified", "deletions": 0, "additions": 31, "changes": 31, "filename": "client/mysql.cc"}, {"status": "modified", "deletions": 2, "additions": 0, "changes": 2, "filename": "mysql-test/r/mysql.result"}, {"status": "modified", "deletions": 6, "additions": 0, "changes": 6, "filename": "mysql-test/t/mysql_delimiter.sql"}], "stats": {"deletions": 8, "additions": 31, "total": 39}, "commit": {"date": "2008-07-17T18:20:01Z", "authorId": "", "author": "Davi Arnaut"}}