{"repo": "mysql", "files": [{"status": "modified", "deletions": 0, "additions": 36, "changes": 36, "filename": "mysql-test/r/subselect.result"}, {"status": "modified", "deletions": 0, "additions": 35, "changes": 35, "filename": "mysql-test/t/subselect.test"}, {"status": "modified", "deletions": 2, "additions": 2, "changes": 4, "filename": "sql/item_cmpfunc.cc"}], "stats": {"deletions": 2, "additions": 73, "total": 75}, "commit": {"date": "2009-01-28T19:18:27Z", "authorId": "", "author": "Sergey Petrunia"}}