{"repo": "webrat", "files": [{"status": "modified", "deletions": 1, "additions": 0, "changes": 1, "filename": "spec/integration/rails/app/views/buttons/show.html.erb"}, {"status": "modified", "deletions": 1, "additions": 0, "changes": 1, "filename": "spec/integration/rails/app/views/webrat/buttons.html.erb"}, {"status": "modified", "deletions": 15, "additions": 0, "changes": 15, "filename": "spec/integration/rails/test/integration/button_click_test.rb"}], "stats": {"deletions": 17, "additions": 0, "total": 17}, "commit": {"date": "2009-11-14T01:57:55Z", "authorId": "brynary", "author": "Bryan Helmkamp"}}