{"repo": "twitter4j", "files": [{"status": "modified", "deletions": 0, "additions": 19, "changes": 19, "filename": "src/main/java/twitter4j/AsyncTwitter.java"}, {"status": "modified", "deletions": 0, "additions": 23, "changes": 23, "filename": "src/main/java/twitter4j/Twitter.java"}, {"status": "modified", "deletions": 0, "additions": 6, "changes": 6, "filename": "src/main/java/twitter4j/TwitterAdapter.java"}, {"status": "modified", "deletions": 0, "additions": 5, "changes": 5, "filename": "src/main/java/twitter4j/TwitterListener.java"}, {"status": "modified", "deletions": 0, "additions": 17, "changes": 17, "filename": "src/test/java/twitter4j/AsyncTwitterTest.java"}, {"status": "modified", "deletions": 0, "additions": 3, "changes": 3, "filename": "src/test/java/twitter4j/TwitterTestUnit.java"}, {"status": "modified", "deletions": 0, "additions": 2, "changes": 2, "filename": "test.properties"}], "stats": {"deletions": 0, "additions": 75, "total": 75}, "commit": {"date": "2009-05-13T15:59:57Z", "authorId": "", "author": "yusuke"}}