{"repo": "snowflake", "files": [{"status": "modified", "deletions": 0, "additions": 1, "changes": 1, "filename": "project/build/Snowflake.scala"}, {"status": "modified", "deletions": 1, "additions": 1, "changes": 2, "filename": "src/test/scala/com/twitter/service/snowflake/IdWorkerSpec.scala"}, {"status": "modified", "deletions": 1, "additions": 1, "changes": 2, "filename": "src/test/scala/com/twitter/service/snowflake/SnowflakeSpec.scala"}], "stats": {"deletions": 2, "additions": 3, "total": 5}, "commit": {"date": "2010-03-17T00:58:56Z", "authorId": "jmhodges", "author": "Jeff Hodges"}}