{"repo": "joauth", "files": [{"status": "modified", "deletions": 1, "additions": 1, "changes": 2, "filename": "project/build.properties"}, {"status": "modified", "deletions": 21, "additions": 9, "changes": 30, "filename": "src/main/scala/com/twitter/joauth/Unpacker.scala"}, {"status": "modified", "deletions": 5, "additions": 2, "changes": 7, "filename": "src/test/scala/com/twitter/joauth/UnpackerSpec.scala"}], "stats": {"deletions": 27, "additions": 12, "total": 39}, "commit": {"date": "2010-10-21T17:02:58Z", "authorId": "9len", "author": "Glen D Sanford"}}