{"repo": "cascading", "files": [{"status": "modified", "deletions": 0, "additions": 2, "changes": 2, "filename": "CHANGES.txt"}, {"status": "modified", "deletions": 1, "additions": 47, "changes": 48, "filename": "src/core/cascading/cascade/Cascade.java"}, {"status": "modified", "deletions": 1, "additions": 1, "changes": 2, "filename": "src/core/cascading/cascade/CascadeConnector.java"}], "stats": {"deletions": 2, "additions": 50, "total": 52}, "commit": {"date": "2010-07-30T21:04:41Z", "authorId": "cwensel", "author": "Chris K Wensel"}}