{"repo": "twitter-text-java", "files": [{"status": "modified", "deletions": 2, "additions": 2, "changes": 4, "filename": "build.xml"}, {"status": "renamed", "deletions": 1, "additions": 1, "changes": 2, "filename": "docs/api/allclasses-frame.html"}, {"status": "renamed", "deletions": 1, "additions": 1, "changes": 2, "filename": "docs/api/allclasses-noframe.html"}, {"status": "renamed", "deletions": 1, "additions": 1, "changes": 2, "filename": "docs/api/com/twitter/Autolink.html"}, {"status": "renamed", "deletions": 1, "additions": 1, "changes": 2, "filename": "docs/api/com/twitter/Extractor.html"}, {"status": "renamed", "deletions": 1, "additions": 1, "changes": 2, "filename": "docs/api/com/twitter/Regex.html"}, {"status": "renamed", "deletions": 1, "additions": 1, "changes": 2, "filename": "docs/api/com/twitter/class-use/Autolink.html"}, {"status": "renamed", "deletions": 1, "additions": 1, "changes": 2, "filename": "docs/api/com/twitter/class-use/Extractor.html"}, {"status": "renamed", "deletions": 1, "additions": 1, "changes": 2, "filename": "docs/api/com/twitter/class-use/Regex.html"}, {"status": "renamed", "deletions": 1, "additions": 1, "changes": 2, "filename": "docs/api/com/twitter/package-frame.html"}, {"status": "renamed", "deletions": 1, "additions": 1, "changes": 2, "filename": "docs/api/com/twitter/package-summary.html"}, {"status": "renamed", "deletions": 1, "additions": 1, "changes": 2, "filename": "docs/api/com/twitter/package-tree.html"}, {"status": "renamed", "deletions": 1, "additions": 1, "changes": 2, "filename": "docs/api/com/twitter/package-use.html"}, {"status": "renamed", "deletions": 1, "additions": 1, "changes": 2, "filename": "docs/api/com/twitter/regex/Spaces.html"}, {"status": "renamed", "deletions": 1, "additions": 1, "changes": 2, "filename": "docs/api/com/twitter/regex/class-use/Spaces.html"}, {"status": "renamed", "deletions": 1, "additions": 1, "changes": 2, "filename": "docs/api/com/twitter/regex/package-frame.html"}, {"status": "renamed", "deletions": 1, "additions": 1, "changes": 2, "filename": "docs/api/com/twitter/regex/package-summary.html"}, {"status": "renamed", "deletions": 1, "additions": 1, "changes": 2, "filename": "docs/api/com/twitter/regex/package-tree.html"}, {"status": "renamed", "deletions": 1, "additions": 1, "changes": 2, "filename": "docs/api/com/twitter/regex/package-use.html"}, {"status": "renamed", "deletions": 1, "additions": 1, "changes": 2, "filename": "docs/api/constant-values.html"}, {"status": "renamed", "deletions": 1, "additions": 1, "changes": 2, "filename": "docs/api/deprecated-list.html"}, {"status": "renamed", "deletions": 1, "additions": 1, "changes": 2, "filename": "docs/api/help-doc.html"}, {"status": "renamed", "deletions": 1, "additions": 1, "changes": 2, "filename": "docs/api/index-all.html"}, {"status": "renamed", "deletions": 1, "additions": 1, "changes": 2, "filename": "docs/api/index.html"}, {"status": "renamed", "deletions": 1, "additions": 1, "changes": 2, "filename": "docs/api/overview-frame.html"}, {"status": "renamed", "deletions": 1, "additions": 1, "changes": 2, "filename": "docs/api/overview-summary.html"}, {"status": "renamed", "deletions": 1, "additions": 1, "changes": 2, "filename": "docs/api/overview-tree.html"}, {"status": "renamed", "deletions": 0, "additions": 0, "changes": 0, "filename": "docs/api/package-list"}, {"status": "renamed", "deletions": 0, "additions": 0, "changes": 0, "filename": "docs/api/resources/inherit.gif"}, {"status": "renamed", "deletions": 0, "additions": 0, "changes": 0, "filename": "docs/api/stylesheet.css"}], "stats": {"deletions": 28, "additions": 28, "total": 56}, "commit": {"date": "2010-01-20T22:37:06Z", "authorId": "", "author": "Matt Sanford"}}