{"repo": "util", "files": [{"status": "modified", "deletions": 4, "additions": 4, "changes": 8, "filename": "src/main/scala/com/twitter/util/Future.scala"}, {"status": "modified", "deletions": 16, "additions": 16, "changes": 32, "filename": "src/main/scala/com/twitter/util/Pool.scala"}, {"status": "modified", "deletions": 2, "additions": 4, "changes": 6, "filename": "src/main/scala/com/twitter/util/Try.scala"}, {"status": "modified", "deletions": 1, "additions": 1, "changes": 2, "filename": "src/test/scala/com/twitter/util/FutureSpec.scala"}, {"status": "modified", "deletions": 1, "additions": 1, "changes": 2, "filename": "src/test/scala/com/twitter/util/PoolSpec.scala"}], "stats": {"deletions": 24, "additions": 26, "total": 50}, "commit": {"date": "2010-08-29T06:06:51Z", "authorId": "", "author": "Nick Kallen"}}