{"repo": "mysql", "files": [{"status": "modified", "deletions": 0, "additions": 0, "changes": 0, "filename": ".bzrfileids"}, {"status": "modified", "deletions": 0, "additions": 17, "changes": 17, "filename": "BUILD/FINISH.sh"}, {"status": "modified", "deletions": 2, "additions": 2, "changes": 4, "filename": "BUILD/Makefile.am"}, {"status": "modified", "deletions": 0, "additions": 17, "changes": 17, "filename": "BUILD/SETUP.sh"}, {"status": "modified", "deletions": 0, "additions": 18, "changes": 18, "filename": "BUILD/autorun.sh"}, {"status": "modified", "deletions": 0, "additions": 17, "changes": 17, "filename": "BUILD/build_mccge.sh"}, {"status": "modified", "deletions": 0, "additions": 16, "changes": 16, "filename": "BUILD/check-cpu"}, {"status": "modified", "deletions": 0, "additions": 15, "changes": 15, "filename": "BUILD/cleanup"}, {"status": "modified", "deletions": 0, "additions": 15, "changes": 15, "filename": "BUILD/compile-alpha"}, {"status": "modified", "deletions": 0, "additions": 15, "changes": 15, "filename": "BUILD/compile-alpha-ccc"}, {"status": "modified", "deletions": 0, "additions": 15, "changes": 15, "filename": "BUILD/compile-alpha-cxx"}, {"status": "modified", "deletions": 0, "additions": 15, "changes": 15, "filename": "BUILD/compile-alpha-debug"}, {"status": "modified", "deletions": 0, "additions": 16, "changes": 16, "filename": "BUILD/compile-amd64-debug-max"}, {"status": "modified", "deletions": 0, "additions": 18, "changes": 18, "filename": "BUILD/compile-amd64-debug-max-no-ndb"}, {"status": "modified", "deletions": 0, "additions": 15, "changes": 15, "filename": "BUILD/compile-amd64-gcov"}, {"status": "modified", "deletions": 0, "additions": 15, "changes": 15, "filename": "BUILD/compile-amd64-gprof"}, {"status": "modified", "deletions": 0, "additions": 15, "changes": 15, "filename": "BUILD/compile-amd64-max"}, {"status": "modified", "deletions": 0, "additions": 15, "changes": 15, "filename": "BUILD/compile-amd64-max-sci"}, {"status": "modified", "deletions": 0, "additions": 17, "changes": 17, "filename": "BUILD/compile-amd64-valgrind-max"}, {"status": "modified", "deletions": 0, "additions": 15, "changes": 15, "filename": "BUILD/compile-darwin-mwcc"}, {"status": "modified", "deletions": 0, "additions": 16, "changes": 16, "filename": "BUILD/compile-dist"}, {"status": "modified", "deletions": 0, "additions": 15, "changes": 15, "filename": "BUILD/compile-hpux11-parisc2-aCC"}, {"status": "modified", "deletions": 0, "additions": 17, "changes": 17, "filename": "BUILD/compile-ia64-debug-max"}, {"status": "modified", "deletions": 0, "additions": 15, "changes": 15, "filename": "BUILD/compile-irix-mips64-mipspro"}, {"status": "modified", "deletions": 0, "additions": 15, "changes": 15, "filename": "BUILD/compile-ndb-autotest"}, {"status": "modified", "deletions": 0, "additions": 15, "changes": 15, "filename": "BUILD/compile-pentium"}, {"status": "modified", "deletions": 0, "additions": 15, "changes": 15, "filename": "BUILD/compile-pentium-cybozu"}, {"status": "modified", "deletions": 0, "additions": 15, "changes": 15, "filename": "BUILD/compile-pentium-debug"}, {"status": "modified", "deletions": 0, "additions": 15, "changes": 15, "filename": "BUILD/compile-pentium-debug-max"}, {"status": "modified", "deletions": 0, "additions": 15, "changes": 15, "filename": "BUILD/compile-pentium-debug-max-no-embedded"}, {"status": "modified", "deletions": 0, "additions": 15, "changes": 15, "filename": "BUILD/compile-pentium-debug-max-no-ndb"}, {"status": "modified", "deletions": 0, "additions": 15, "changes": 15, "filename": "BUILD/compile-pentium-debug-openssl"}, {"status": "modified", "deletions": 0, "additions": 15, "changes": 15, "filename": "BUILD/compile-pentium-debug-yassl"}, {"status": "modified", "deletions": 0, "additions": 15, "changes": 15, "filename": "BUILD/compile-pentium-gcov"}, {"status": "modified", "deletions": 0, "additions": 15, "changes": 15, "filename": "BUILD/compile-pentium-gprof"}, {"status": "modified", "deletions": 0, "additions": 15, "changes": 15, "filename": "BUILD/compile-pentium-icc"}, {"status": "modified", "deletions": 0, "additions": 15, "changes": 15, "filename": "BUILD/compile-pentium-icc-valgrind-max"}, {"status": "modified", "deletions": 0, "additions": 15, "changes": 15, "filename": "BUILD/compile-pentium-icc-yassl"}, {"status": "modified", "deletions": 0, "additions": 15, "changes": 15, "filename": "BUILD/compile-pentium-max"}, {"status": "modified", "deletions": 0, "additions": 15, "changes": 15, "filename": "BUILD/compile-pentium-myodbc"}, {"status": "modified", "deletions": 0, "additions": 15, "changes": 15, "filename": "BUILD/compile-pentium-mysqlfs-debug"}, {"status": "modified", "deletions": 0, "additions": 15, "changes": 15, "filename": "BUILD/compile-pentium-pgcc"}, {"status": "modified", "deletions": 0, "additions": 15, "changes": 15, "filename": "BUILD/compile-pentium-valgrind-max"}, {"status": "modified", "deletions": 0, "additions": 17, "changes": 17, "filename": "BUILD/compile-pentium-valgrind-max-no-ndb"}, {"status": "modified", "deletions": 0, "additions": 17, "changes": 17, "filename": "BUILD/compile-pentium64"}, {"status": "modified", "deletions": 0, "additions": 15, "changes": 15, "filename": "BUILD/compile-pentium64-debug"}, {"status": "modified", "deletions": 0, "additions": 15, "changes": 15, "filename": "BUILD/compile-pentium64-debug-max"}, {"status": "modified", "deletions": 0, "additions": 15, "changes": 15, "filename": "BUILD/compile-pentium64-gcov"}, {"status": "modified", "deletions": 0, "additions": 15, "changes": 15, "filename": "BUILD/compile-pentium64-gprof"}, {"status": "modified", "deletions": 0, "additions": 17, "changes": 17, "filename": "BUILD/compile-pentium64-max"}, {"status": "modified", "deletions": 0, "additions": 15, "changes": 15, "filename": "BUILD/compile-pentium64-max-sci"}, {"status": "modified", "deletions": 0, "additions": 15, "changes": 15, "filename": "BUILD/compile-pentium64-valgrind-max"}, {"status": "modified", "deletions": 0, "additions": 15, "changes": 15, "filename": "BUILD/compile-ppc"}, {"status": "modified", "deletions": 0, "additions": 15, "changes": 15, "filename": "BUILD/compile-ppc-debug"}, {"status": "modified", "deletions": 0, "additions": 15, "changes": 15, "filename": "BUILD/compile-ppc-debug-max"}, {"status": "modified", "deletions": 0, "additions": 15, "changes": 15, "filename": "BUILD/compile-ppc-debug-max-no-ndb"}, {"status": "modified", "deletions": 0, "additions": 15, "changes": 15, "filename": "BUILD/compile-ppc-max"}, {"status": "modified", "deletions": 0, "additions": 17, "changes": 17, "filename": "BUILD/compile-solaris-amd64"}, {"status": "modified", "deletions": 0, "additions": 16, "changes": 16, "filename": "BUILD/compile-solaris-amd64-debug"}, {"status": "modified", "deletions": 0, "additions": 15, "changes": 15, "filename": "BUILD/compile-solaris-amd64-forte"}, {"status": "modified", "deletions": 0, "additions": 15, "changes": 15, "filename": "BUILD/compile-solaris-amd64-forte-debug"}, {"status": "modified", "deletions": 0, "additions": 15, "changes": 15, "filename": "BUILD/compile-solaris-sparc"}, {"status": "modified", "deletions": 0, "additions": 15, "changes": 15, "filename": "BUILD/compile-solaris-sparc-debug"}, {"status": "modified", "deletions": 0, "additions": 15, "changes": 15, "filename": "BUILD/compile-solaris-sparc-forte"}, {"status": "modified", "deletions": 0, "additions": 15, "changes": 15, "filename": "BUILD/compile-solaris-sparc-purify"}, {"status": "modified", "deletions": 1, "additions": 1, "changes": 2, "filename": "Makefile.am"}, {"status": "modified", "deletions": 2, "additions": 2, "changes": 4, "filename": "client/completion_hash.h"}, {"status": "modified", "deletions": 0, "additions": 15, "changes": 15, "filename": "dbug/dbug_add_tags.pl"}, {"status": "modified", "deletions": 1, "additions": 1, "changes": 2, "filename": "extra/yassl/CMakeLists.txt"}, {"status": "modified", "deletions": 0, "additions": 15, "changes": 15, "filename": "extra/yassl/Makefile.am"}, {"status": "modified", "deletions": 0, "additions": 18, "changes": 18, "filename": "extra/yassl/examples/client/client.cpp"}, {"status": "modified", "deletions": 0, "additions": 18, "changes": 18, "filename": "extra/yassl/examples/echoclient/echoclient.cpp"}, {"status": "modified", "deletions": 0, "additions": 18, "changes": 18, "filename": "extra/yassl/examples/echoserver/echoserver.cpp"}, {"status": "modified", "deletions": 0, "additions": 18, "changes": 18, "filename": "extra/yassl/examples/server/server.cpp"}, {"status": "modified", "deletions": 1, "additions": 1, "changes": 2, "filename": "extra/yassl/include/lock.hpp"}, {"status": "modified", "deletions": 0, "additions": 18, "changes": 18, "filename": "extra/yassl/include/openssl/crypto.h"}, {"status": "modified", "deletions": 0, "additions": 18, "changes": 18, "filename": "extra/yassl/include/openssl/des.h"}, {"status": "modified", "deletions": 0, "additions": 18, "changes": 18, "filename": "extra/yassl/include/openssl/des_old.h"}, {"status": "modified", "deletions": 0, "additions": 18, "changes": 18, "filename": "extra/yassl/include/openssl/engine.h"}, {"status": "modified", "deletions": 0, "additions": 18, "changes": 18, "filename": "extra/yassl/include/openssl/err.h"}, {"status": "modified", "deletions": 0, "additions": 18, "changes": 18, "filename": "extra/yassl/include/openssl/evp.h"}, {"status": "modified", "deletions": 0, "additions": 16, "changes": 16, "filename": "extra/yassl/include/openssl/generate_prefix_files.pl"}, {"status": "modified", "deletions": 0, "additions": 18, "changes": 18, "filename": "extra/yassl/include/openssl/hmac.h"}, {"status": "modified", "deletions": 0, "additions": 18, "changes": 18, "filename": "extra/yassl/include/openssl/lhash.h"}, {"status": "modified", "deletions": 0, "additions": 18, "changes": 18, "filename": "extra/yassl/include/openssl/md4.h"}, {"status": "modified", "deletions": 0, "additions": 18, "changes": 18, "filename": "extra/yassl/include/openssl/md5.h"}, {"status": "modified", "deletions": 0, "additions": 18, "changes": 18, "filename": "extra/yassl/include/openssl/objects.h"}, {"status": "modified", "deletions": 0, "additions": 18, "changes": 18, "filename": "extra/yassl/include/openssl/opensslv.h"}, {"status": "modified", "deletions": 0, "additions": 18, "changes": 18, "filename": "extra/yassl/include/openssl/pem.h"}, {"status": "modified", "deletions": 0, "additions": 18, "changes": 18, "filename": "extra/yassl/include/openssl/pkcs12.h"}, {"status": "modified", "deletions": 0, "additions": 18, "changes": 18, "filename": "extra/yassl/include/openssl/prefix_crypto.h"}, {"status": "modified", "deletions": 0, "additions": 18, "changes": 18, "filename": "extra/yassl/include/openssl/prefix_ssl.h"}, {"status": "modified", "deletions": 0, "additions": 18, "changes": 18, "filename": "extra/yassl/include/openssl/rand.h"}, {"status": "modified", "deletions": 0, "additions": 18, "changes": 18, "filename": "extra/yassl/include/openssl/rsa.h"}, {"status": "modified", "deletions": 0, "additions": 18, "changes": 18, "filename": "extra/yassl/include/openssl/sha.h"}, {"status": "modified", "deletions": 0, "additions": 18, "changes": 18, "filename": "extra/yassl/include/openssl/x509.h"}, {"status": "modified", "deletions": 0, "additions": 18, "changes": 18, "filename": "extra/yassl/include/openssl/x509v3.h"}, {"status": "modified", "deletions": 0, "additions": 15, "changes": 15, "filename": "extra/yassl/src/Makefile.am"}, {"status": "modified", "deletions": 1, "additions": 1, "changes": 2, "filename": "extra/yassl/src/lock.cpp"}, {"status": "modified", "deletions": 0, "additions": 15, "changes": 15, "filename": "extra/yassl/src/make.bat"}, {"status": "modified", "deletions": 1, "additions": 1, "changes": 2, "filename": "extra/yassl/taocrypt/CMakeLists.txt"}, {"status": "modified", "deletions": 0, "additions": 15, "changes": 15, "filename": "extra/yassl/taocrypt/Makefile.am"}, {"status": "modified", "deletions": 0, "additions": 15, "changes": 15, "filename": "extra/yassl/taocrypt/benchmark/Makefile.am"}, {"status": "modified", "deletions": 0, "additions": 18, "changes": 18, "filename": "extra/yassl/taocrypt/benchmark/benchmark.cpp"}, {"status": "modified", "deletions": 0, "additions": 15, "changes": 15, "filename": "extra/yassl/taocrypt/benchmark/make.bat"}, {"status": "modified", "deletions": 0, "additions": 15, "changes": 15, "filename": "extra/yassl/taocrypt/src/Makefile.am"}, {"status": "modified", "deletions": 0, "additions": 15, "changes": 15, "filename": "extra/yassl/taocrypt/src/make.bat"}, {"status": "modified", "deletions": 0, "additions": 15, "changes": 15, "filename": "extra/yassl/taocrypt/test/Makefile.am"}, {"status": "modified", "deletions": 0, "additions": 15, "changes": 15, "filename": "extra/yassl/taocrypt/test/make.bat"}, {"status": "modified", "deletions": 0, "additions": 18, "changes": 18, "filename": "extra/yassl/taocrypt/test/memory.cpp"}, {"status": "modified", "deletions": 0, "additions": 18, "changes": 18, "filename": "extra/yassl/taocrypt/test/test.cpp"}, {"status": "modified", "deletions": 0, "additions": 15, "changes": 15, "filename": "extra/yassl/testsuite/Makefile.am"}, {"status": "modified", "deletions": 0, "additions": 15, "changes": 15, "filename": "extra/yassl/testsuite/make.bat"}, {"status": "modified", "deletions": 0, "additions": 18, "changes": 18, "filename": "extra/yassl/testsuite/test.hpp"}, {"status": "modified", "deletions": 0, "additions": 18, "changes": 18, "filename": "extra/yassl/testsuite/testsuite.cpp"}, {"status": "modified", "deletions": 2, "additions": 2, "changes": 4, "filename": "include/Makefile.am"}, {"status": "modified", "deletions": 2, "additions": 2, "changes": 4, "filename": "include/my_handler.h"}, {"status": "modified", "deletions": 1, "additions": 1, "changes": 2, "filename": "include/my_sys.h"}, {"status": "modified", "deletions": 1, "additions": 1, "changes": 2, "filename": "include/mysql_com.h"}, {"status": "removed", "deletions": 14, "additions": 0, "changes": 14, "filename": "libmysqld/copyright"}, {"status": "modified", "deletions": 0, "additions": 15, "changes": 15, "filename": "libmysqld/examples/test-run"}, {"status": "modified", "deletions": 2, "additions": 2, "changes": 4, "filename": "man/Makefile.am"}, {"status": "modified", "deletions": 2, "additions": 2, "changes": 4, "filename": "mysql-test/Makefile.am"}, {"status": "modified", "deletions": 2, "additions": 2, "changes": 4, "filename": "mysql-test/lib/mtr_cases.pm"}, {"status": "modified", "deletions": 1, "additions": 1, "changes": 2, "filename": "mysql-test/lib/mtr_process.pl"}, {"status": "modified", "deletions": 0, "additions": 18, "changes": 18, "filename": "mysql-test/mysql-stress-test.pl"}, {"status": "modified", "deletions": 0, "additions": 17, "changes": 17, "filename": "mysql-test/mysql-test-run.pl"}, {"status": "modified", "deletions": 0, "additions": 17, "changes": 17, "filename": "mysql-test/purify.supp"}, {"status": "modified", "deletions": 0, "additions": 18, "changes": 18, "filename": "mysql-test/valgrind.supp"}, {"status": "modified", "deletions": 1, "additions": 1, "changes": 2, "filename": "mysys/mf_pack.c"}, {"status": "modified", "deletions": 0, "additions": 15, "changes": 15, "filename": "scripts/fill_help_tables.sql"}, {"status": "modified", "deletions": 1, "additions": 1, "changes": 2, "filename": "scripts/make_binary_distribution.sh"}, {"status": "modified", "deletions": 1, "additions": 1, "changes": 2, "filename": "scripts/make_win_bin_dist"}, {"status": "modified", "deletions": 0, "additions": 18, "changes": 18, "filename": "scripts/mysql_fix_extensions.sh"}, {"status": "modified", "deletions": 0, "additions": 18, "changes": 18, "filename": "scripts/mysql_setpermission.sh"}, {"status": "modified", "deletions": 0, "additions": 15, "changes": 15, "filename": "scripts/mysql_system_tables.sql"}, {"status": "modified", "deletions": 0, "additions": 15, "changes": 15, "filename": "scripts/mysql_system_tables_data.sql"}, {"status": "modified", "deletions": 0, "additions": 15, "changes": 15, "filename": "scripts/mysql_system_tables_fix.sql"}, {"status": "modified", "deletions": 0, "additions": 15, "changes": 15, "filename": "scripts/mysql_test_data_timezone.sql"}, {"status": "modified", "deletions": 0, "additions": 18, "changes": 18, "filename": "scripts/mysqlaccess.sh"}, {"status": "modified", "deletions": 0, "additions": 17, "changes": 17, "filename": "scripts/mysqld_multi.sh"}, {"status": "modified", "deletions": 0, "additions": 18, "changes": 18, "filename": "scripts/mysqldumpslow.sh"}, {"status": "modified", "deletions": 0, "additions": 17, "changes": 17, "filename": "scripts/mysqlhotcopy.sh"}, {"status": "modified", "deletions": 2, "additions": 2, "changes": 4, "filename": "server-tools/instance-manager/options.cc"}, {"status": "modified", "deletions": 1, "additions": 1, "changes": 2, "filename": "sql/field.cc"}, {"status": "modified", "deletions": 2, "additions": 2, "changes": 4, "filename": "sql/gen_lex_hash.cc"}, {"status": "modified", "deletions": 1, "additions": 1, "changes": 2, "filename": "sql/item.h"}, {"status": "modified", "deletions": 1, "additions": 1, "changes": 2, "filename": "sql/item_cmpfunc.cc"}, {"status": "modified", "deletions": 1, "additions": 1, "changes": 2, "filename": "sql/item_cmpfunc.h"}, {"status": "modified", "deletions": 1, "additions": 1, "changes": 2, "filename": "sql/item_func.cc"}, {"status": "modified", "deletions": 1, "additions": 1, "changes": 2, "filename": "sql/item_func.h"}, {"status": "modified", "deletions": 1, "additions": 1, "changes": 2, "filename": "sql/item_subselect.cc"}, {"status": "modified", "deletions": 1, "additions": 1, "changes": 2, "filename": "sql/item_sum.cc"}, {"status": "modified", "deletions": 0, "additions": 15, "changes": 15, "filename": "sql/message.h"}, {"status": "modified", "deletions": 1, "additions": 1, "changes": 2, "filename": "sql/mysqld.cc"}, {"status": "modified", "deletions": 1, "additions": 1, "changes": 2, "filename": "sql/net_serv.cc"}, {"status": "modified", "deletions": 1, "additions": 1, "changes": 2, "filename": "sql/opt_range.cc"}, {"status": "modified", "deletions": 1, "additions": 1, "changes": 2, "filename": "sql/set_var.cc"}, {"status": "modified", "deletions": 1, "additions": 1, "changes": 2, "filename": "sql/set_var.h"}, {"status": "modified", "deletions": 0, "additions": 16, "changes": 16, "filename": "sql/share/charsets/languages.html"}, {"status": "modified", "deletions": 1, "additions": 1, "changes": 2, "filename": "sql/sql_base.cc"}, {"status": "modified", "deletions": 1, "additions": 1, "changes": 2, "filename": "sql/sql_class.h"}, {"status": "modified", "deletions": 1, "additions": 1, "changes": 2, "filename": "sql/sql_parse.cc"}, {"status": "modified", "deletions": 1, "additions": 1, "changes": 2, "filename": "sql/sql_prepare.cc"}, {"status": "modified", "deletions": 1, "additions": 1, "changes": 2, "filename": "sql/sql_select.cc"}, {"status": "modified", "deletions": 1, "additions": 1, "changes": 2, "filename": "sql/sql_select.h"}, {"status": "modified", "deletions": 1, "additions": 1, "changes": 2, "filename": "sql/sql_show.cc"}, {"status": "modified", "deletions": 1, "additions": 1, "changes": 2, "filename": "sql/sql_update.cc"}, {"status": "modified", "deletions": 1, "additions": 1, "changes": 2, "filename": "sql/table.h"}, {"status": "modified", "deletions": 1, "additions": 1, "changes": 2, "filename": "storage/heap/hp_delete.c"}, {"status": "modified", "deletions": 0, "additions": 15, "changes": 15, "filename": "storage/myisam/ftbench/Ecompare.pl"}, {"status": "modified", "deletions": 0, "additions": 15, "changes": 15, "filename": "storage/myisam/ftbench/Ecreate.pl"}, {"status": "modified", "deletions": 0, "additions": 15, "changes": 15, "filename": "storage/myisam/ftbench/Ereport.pl"}, {"status": "modified", "deletions": 0, "additions": 17, "changes": 17, "filename": "storage/myisam/ftbench/ft-test-run.sh"}, {"status": "modified", "deletions": 0, "additions": 18, "changes": 18, "filename": "storage/myisam/mi_test_all.sh"}, {"status": "modified", "deletions": 1, "additions": 1, "changes": 2, "filename": "storage/myisam/myisampack.c"}, {"status": "modified", "deletions": 1, "additions": 1, "changes": 2, "filename": "storage/myisam/rt_index.c"}, {"status": "modified", "deletions": 1, "additions": 1, "changes": 2, "filename": "storage/ndb/Makefile.am"}, {"status": "modified", "deletions": 0, "additions": 14, "changes": 14, "filename": "storage/ndb/config/make-win-dsw.sh"}, {"status": "modified", "deletions": 0, "additions": 15, "changes": 15, "filename": "storage/ndb/config/win-includes"}, {"status": "modified", "deletions": 0, "additions": 15, "changes": 15, "filename": "storage/ndb/config/win-libraries"}, {"status": "modified", "deletions": 0, "additions": 15, "changes": 15, "filename": "storage/ndb/config/win-name"}, {"status": "modified", "deletions": 0, "additions": 15, "changes": 15, "filename": "storage/ndb/config/win-sources"}, {"status": "modified", "deletions": 1, "additions": 1, "changes": 2, "filename": "storage/ndb/docs/Makefile.am"}, {"status": "modified", "deletions": 1, "additions": 16, "changes": 17, "filename": "storage/ndb/docs/doxygen/Doxyfile.mgmapi"}, {"status": "modified", "deletions": 0, "additions": 15, "changes": 15, "filename": "storage/ndb/docs/doxygen/Doxyfile.ndb"}, {"status": "modified", "deletions": 1, "additions": 16, "changes": 17, "filename": "storage/ndb/docs/doxygen/Doxyfile.ndbapi"}, {"status": "modified", "deletions": 0, "additions": 15, "changes": 15, "filename": "storage/ndb/docs/doxygen/Doxyfile.odbc"}, {"status": "removed", "deletions": 44, "additions": 0, "changes": 44, "filename": "storage/ndb/docs/doxygen/header.mgmapi.tex"}, {"status": "removed", "deletions": 44, "additions": 0, "changes": 44, "filename": "storage/ndb/docs/doxygen/header.ndbapi.tex"}, {"status": "modified", "deletions": 0, "additions": 15, "changes": 15, "filename": "storage/ndb/docs/doxygen/postdoxy.pl"}, {"status": "modified", "deletions": 0, "additions": 15, "changes": 15, "filename": "storage/ndb/docs/doxygen/predoxy.pl"}, {"status": "modified", "deletions": 0, "additions": 15, "changes": 15, "filename": "storage/ndb/src/cw/cpcc-win32/csharp/CPC_Form.cs"}, {"status": "modified", "deletions": 0, "additions": 15, "changes": 15, "filename": "storage/ndb/src/cw/cpcc-win32/csharp/Computer.cs"}, {"status": "modified", "deletions": 0, "additions": 15, "changes": 15, "filename": "storage/ndb/src/cw/cpcc-win32/csharp/ComputerAddDialog.cs"}, {"status": "modified", "deletions": 0, "additions": 15, "changes": 15, "filename": "storage/ndb/src/cw/cpcc-win32/csharp/ComputerRemoveDialog.cs"}, {"status": "modified", "deletions": 0, "additions": 15, "changes": 15, "filename": "storage/ndb/src/cw/cpcc-win32/csharp/Database.cs"}, {"status": "modified", "deletions": 0, "additions": 15, "changes": 15, "filename": "storage/ndb/src/cw/cpcc-win32/csharp/PanelWizard.cs"}, {"status": "modified", "deletions": 0, "additions": 15, "changes": 15, "filename": "storage/ndb/src/cw/cpcc-win32/csharp/Process.cs"}, {"status": "modified", "deletions": 0, "additions": 15, "changes": 15, "filename": "storage/ndb/src/cw/cpcc-win32/csharp/ProcessDefineDialog.cs"}, {"status": "modified", "deletions": 0, "additions": 15, "changes": 15, "filename": "storage/ndb/src/cw/cpcc-win32/csharp/fileaccess/FileMgmt.cs"}, {"status": "modified", "deletions": 0, "additions": 15, "changes": 15, "filename": "storage/ndb/src/cw/cpcc-win32/csharp/simpleparser/SimpleCPCParser.cs"}, {"status": "modified", "deletions": 0, "additions": 15, "changes": 15, "filename": "storage/ndb/src/cw/cpcc-win32/csharp/socketcomm/SocketComm.cs"}, {"status": "modified", "deletions": 0, "additions": 15, "changes": 15, "filename": "storage/ndb/src/cw/cpcc-win32/csharp/socketcomm/myTcpClient.cs"}, {"status": "modified", "deletions": 0, "additions": 15, "changes": 15, "filename": "storage/ndb/src/cw/cpcc-win32/csharp/startDatabaseDlg.cs"}, {"status": "modified", "deletions": 0, "additions": 15, "changes": 15, "filename": "storage/ndb/src/cw/cpcc-win32/csharp/telnetclient/telnetClient.cs"}, {"status": "removed", "deletions": 20, "additions": 0, "changes": 20, "filename": "storage/ndb/src/cw/cpcc-win32/vb6/Computer.cls"}, {"status": "removed", "deletions": 18, "additions": 0, "changes": 18, "filename": "storage/ndb/src/cw/cpcc-win32/vb6/Database.cls"}, {"status": "removed", "deletions": 0, "additions": 0, "changes": 0, "filename": "storage/ndb/src/cw/cpcc-win32/vb6/Icon 110.ico"}, {"status": "removed", "deletions": 0, "additions": 0, "changes": 0, "filename": "storage/ndb/src/cw/cpcc-win32/vb6/Icon 231.ico"}, {"status": "removed", "deletions": 0, "additions": 0, "changes": 0, "filename": "storage/ndb/src/cw/cpcc-win32/vb6/Icon 237.ico"}, {"status": "removed", "deletions": 0, "additions": 0, "changes": 0, "filename": "storage/ndb/src/cw/cpcc-win32/vb6/Icon 241.ico"}, {"status": "removed", "deletions": 0, "additions": 0, "changes": 0, "filename": "storage/ndb/src/cw/cpcc-win32/vb6/Icon 242.ico"}, {"status": "removed", "deletions": 0, "additions": 0, "changes": 0, "filename": "storage/ndb/src/cw/cpcc-win32/vb6/Icon 270.ico"}, {"status": "removed", "deletions": 0, "additions": 0, "changes": 0, "filename": "storage/ndb/src/cw/cpcc-win32/vb6/Icon 271.ico"}, {"status": "removed", "deletions": 0, "additions": 0, "changes": 0, "filename": "storage/ndb/src/cw/cpcc-win32/vb6/Icon 273.ico"}, {"status": "removed", "deletions": 0, "additions": 0, "changes": 0, "filename": "storage/ndb/src/cw/cpcc-win32/vb6/Icon 31.ico"}, {"status": "removed", "deletions": 0, "additions": 0, "changes": 0, "filename": "storage/ndb/src/cw/cpcc-win32/vb6/Icon 337.ico"}, {"status": "removed", "deletions": 0, "additions": 0, "changes": 0, "filename": "storage/ndb/src/cw/cpcc-win32/vb6/Icon 338.ico"}, {"status": "removed", "deletions": 0, "additions": 0, "changes": 0, "filename": "storage/ndb/src/cw/cpcc-win32/vb6/Icon 339.ico"}, {"status": "removed", "deletions": 5, "additions": 0, "changes": 5, "filename": "storage/ndb/src/cw/cpcc-win32/vb6/MSSCCPRJ.SCC"}, {"status": "removed", "deletions": 233, "additions": 0, "changes": 233, "filename": "storage/ndb/src/cw/cpcc-win32/vb6/Module1.bas"}, {"status": "removed", "deletions": 49, "additions": 0, "changes": 49, "filename": "storage/ndb/src/cw/cpcc-win32/vb6/NdbCPC.vbp"}, {"status": "removed", "deletions": 13, "additions": 0, "changes": 13, "filename": "storage/ndb/src/cw/cpcc-win32/vb6/NdbCPC.vbw"}, {"status": "removed", "deletions": 22, "additions": 0, "changes": 22, "filename": "storage/ndb/src/cw/cpcc-win32/vb6/Process.cls"}, {"status": "removed", "deletions": 0, "additions": 0, "changes": 0, "filename": "storage/ndb/src/cw/cpcc-win32/vb6/closed folder.ico"}, {"status": "removed", "deletions": 0, "additions": 0, "changes": 0, "filename": "storage/ndb/src/cw/cpcc-win32/vb6/computer.ico"}, {"status": "removed", "deletions": 245, "additions": 0, "changes": 245, "filename": "storage/ndb/src/cw/cpcc-win32/vb6/frmAbout.frm"}, {"status": "removed", "deletions": 119, "additions": 0, "changes": 119, "filename": "storage/ndb/src/cw/cpcc-win32/vb6/frmLogin.frm"}, {"status": "removed", "deletions": 1207, "additions": 0, "changes": 1207, "filename": "storage/ndb/src/cw/cpcc-win32/vb6/frmMain.frm"}, {"status": "removed", "deletions": 124, "additions": 0, "changes": 124, "filename": "storage/ndb/src/cw/cpcc-win32/vb6/frmNewComputer.frm"}, {"status": "removed", "deletions": 0, "additions": 0, "changes": 0, "filename": "storage/ndb/src/cw/cpcc-win32/vb6/frmNewComputer.frx"}, {"status": "removed", "deletions": 0, "additions": 0, "changes": 0, "filename": "storage/ndb/src/cw/cpcc-win32/vb6/frmNewDatabase.frx"}, {"status": "removed", "deletions": 187, "additions": 0, "changes": 187, "filename": "storage/ndb/src/cw/cpcc-win32/vb6/frmNewDatabase1.frm"}, {"status": "removed", "deletions": 136, "additions": 0, "changes": 136, "filename": "storage/ndb/src/cw/cpcc-win32/vb6/frmNewDatabase2.frm"}, {"status": "removed", "deletions": 1, "additions": 0, "changes": 1, "filename": "storage/ndb/src/cw/cpcc-win32/vb6/frmNewDatabase2.log"}, {"status": "removed", "deletions": 88, "additions": 0, "changes": 88, "filename": "storage/ndb/src/cw/cpcc-win32/vb6/frmNewDatabase3.frm"}, {"status": "removed", "deletions": 231, "additions": 0, "changes": 231, "filename": "storage/ndb/src/cw/cpcc-win32/vb6/frmOptions.frm"}, {"status": "removed", "deletions": 0, "additions": 0, "changes": 0, "filename": "storage/ndb/src/cw/cpcc-win32/vb6/frmSplash.frx"}, {"status": "removed", "deletions": 0, "additions": 0, "changes": 0, "filename": "storage/ndb/src/cw/cpcc-win32/vb6/networking.ico"}, {"status": "removed", "deletions": 0, "additions": 0, "changes": 0, "filename": "storage/ndb/src/cw/cpcc-win32/vb6/open folder.ico"}, {"status": "modified", "deletions": 0, "additions": 15, "changes": 15, "filename": "storage/ndb/src/libndb.ver.in"}, {"status": "modified", "deletions": 0, "additions": 14, "changes": 14, "filename": "storage/ndb/test/ndbapi/slow_select.cpp"}, {"status": "modified", "deletions": 0, "additions": 14, "changes": 14, "filename": "storage/ndb/test/ndbapi/testBitfield.cpp"}, {"status": "modified", "deletions": 0, "additions": 14, "changes": 14, "filename": "storage/ndb/test/ndbapi/testLcp.cpp"}, {"status": "modified", "deletions": 0, "additions": 15, "changes": 15, "filename": "storage/ndb/test/ndbnet/test.run"}, {"status": "modified", "deletions": 0, "additions": 17, "changes": 17, "filename": "storage/ndb/test/ndbnet/testError.run"}, {"status": "modified", "deletions": 0, "additions": 17, "changes": 17, "filename": "storage/ndb/test/ndbnet/testMNF.run"}, {"status": "modified", "deletions": 0, "additions": 15, "changes": 15, "filename": "storage/ndb/test/ndbnet/testNR.run"}, {"status": "modified", "deletions": 0, "additions": 17, "changes": 17, "filename": "storage/ndb/test/ndbnet/testNR1.run"}, {"status": "modified", "deletions": 0, "additions": 17, "changes": 17, "filename": "storage/ndb/test/ndbnet/testNR4.run"}, {"status": "modified", "deletions": 0, "additions": 15, "changes": 15, "filename": "storage/ndb/test/ndbnet/testSRhang.run"}, {"status": "modified", "deletions": 0, "additions": 17, "changes": 17, "filename": "storage/ndb/test/ndbnet/testTR295.run"}, {"status": "modified", "deletions": 0, "additions": 15, "changes": 15, "filename": "storage/ndb/test/run-test/16node-tests.txt"}, {"status": "modified", "deletions": 0, "additions": 17, "changes": 17, "filename": "storage/ndb/test/run-test/atrt-analyze-result.sh"}, {"status": "modified", "deletions": 0, "additions": 17, "changes": 17, "filename": "storage/ndb/test/run-test/atrt-clear-result.sh"}, {"status": "modified", "deletions": 0, "additions": 17, "changes": 17, "filename": "storage/ndb/test/run-test/atrt-gather-result.sh"}, {"status": "modified", "deletions": 0, "additions": 17, "changes": 17, "filename": "storage/ndb/test/run-test/atrt-mysql-test-run"}, {"status": "modified", "deletions": 0, "additions": 17, "changes": 17, "filename": "storage/ndb/test/run-test/atrt-setup.sh"}, {"status": "modified", "deletions": 0, "additions": 17, "changes": 17, "filename": "storage/ndb/test/run-test/atrt-testBackup"}, {"status": "modified", "deletions": 0, "additions": 15, "changes": 15, "filename": "storage/ndb/test/run-test/basic.txt"}, {"status": "modified", "deletions": 0, "additions": 15, "changes": 15, "filename": "storage/ndb/test/run-test/daily-basic-tests.txt"}, {"status": "modified", "deletions": 0, "additions": 15, "changes": 15, "filename": "storage/ndb/test/run-test/daily-devel-tests.txt"}, {"status": "modified", "deletions": 0, "additions": 17, "changes": 17, "filename": "storage/ndb/test/run-test/make-config.sh"}, {"status": "modified", "deletions": 0, "additions": 17, "changes": 17, "filename": "storage/ndb/test/run-test/make-html-reports.sh"}, {"status": "modified", "deletions": 0, "additions": 18, "changes": 18, "filename": "storage/ndb/test/run-test/make-index.sh"}, {"status": "modified", "deletions": 0, "additions": 18, "changes": 18, "filename": "storage/ndb/test/run-test/ndb-autotest.sh"}, {"status": "modified", "deletions": 0, "additions": 17, "changes": 17, "filename": "storage/ndb/test/sql/test_create_drop.pl"}, {"status": "modified", "deletions": 0, "additions": 17, "changes": 17, "filename": "storage/ndb/test/sql/test_range_bounds.pl"}, {"status": "modified", "deletions": 0, "additions": 15, "changes": 15, "filename": "storage/ndb/tools/clean-links.sh"}, {"status": "modified", "deletions": 0, "additions": 15, "changes": 15, "filename": "storage/ndb/tools/make-errors.pl"}, {"status": "modified", "deletions": 0, "additions": 15, "changes": 15, "filename": "storage/ndb/tools/make-links.sh"}, {"status": "modified", "deletions": 0, "additions": 15, "changes": 15, "filename": "storage/ndb/tools/ndb_error_reporter"}, {"status": "modified", "deletions": 0, "additions": 15, "changes": 15, "filename": "storage/ndb/tools/rgrep"}, {"status": "modified", "deletions": 0, "additions": 22, "changes": 22, "filename": "strings/strtod.c"}, {"status": "modified", "deletions": 0, "additions": 16, "changes": 16, "filename": "support-files/MacOSX/Description.plist.sh"}, {"status": "modified", "deletions": 0, "additions": 16, "changes": 16, "filename": "support-files/MacOSX/Info.plist.sh"}, {"status": "modified", "deletions": 2, "additions": 2, "changes": 4, "filename": "support-files/MacOSX/Makefile.am"}, {"status": "modified", "deletions": 0, "additions": 16, "changes": 16, "filename": "support-files/MacOSX/MySQLCOM"}, {"status": "modified", "deletions": 0, "additions": 16, "changes": 16, "filename": "support-files/MacOSX/StartupItem.Description.plist"}, {"status": "modified", "deletions": 0, "additions": 16, "changes": 16, "filename": "support-files/MacOSX/StartupItem.Info.plist"}, {"status": "modified", "deletions": 0, "additions": 16, "changes": 16, "filename": "support-files/MacOSX/StartupItem.postinstall"}, {"status": "modified", "deletions": 0, "additions": 16, "changes": 16, "filename": "support-files/MacOSX/StartupParameters.plist.sh"}, {"status": "modified", "deletions": 0, "additions": 15, "changes": 15, "filename": "support-files/MacOSX/mwar-wrapper"}, {"status": "modified", "deletions": 0, "additions": 15, "changes": 15, "filename": "support-files/MacOSX/mwcc-wrapper"}, {"status": "modified", "deletions": 0, "additions": 18, "changes": 18, "filename": "support-files/MacOSX/postflight.sh"}, {"status": "modified", "deletions": 0, "additions": 18, "changes": 18, "filename": "support-files/MacOSX/preflight.sh"}, {"status": "modified", "deletions": 2, "additions": 2, "changes": 4, "filename": "support-files/Makefile.am"}, {"status": "modified", "deletions": 2, "additions": 2, "changes": 4, "filename": "support-files/RHEL4-SElinux/Makefile.am"}, {"status": "modified", "deletions": 0, "additions": 15, "changes": 15, "filename": "support-files/RHEL4-SElinux/mysql.fc"}, {"status": "modified", "deletions": 0, "additions": 14, "changes": 14, "filename": "support-files/RHEL4-SElinux/mysql.te"}, {"status": "removed", "deletions": 29, "additions": 0, "changes": 29, "filename": "support-files/SCO/INSTALL.sh"}, {"status": "removed", "deletions": 102, "additions": 0, "changes": 102, "filename": "support-files/SCO/compile.sh"}, {"status": "removed", "deletions": 17, "additions": 0, "changes": 17, "filename": "support-files/SCO/doc.sh"}, {"status": "removed", "deletions": 47, "additions": 0, "changes": 47, "filename": "support-files/SCO/mkpkg.sh"}, {"status": "removed", "deletions": 96, "additions": 0, "changes": 96, "filename": "support-files/SCO/patch"}, {"status": "removed", "deletions": 8, "additions": 0, "changes": 8, "filename": "support-files/SCO/pkginfo.ini"}, {"status": "removed", "deletions": 30, "additions": 0, "changes": 30, "filename": "support-files/SCO/postinstall"}, {"status": "removed", "deletions": 21, "additions": 0, "changes": 21, "filename": "support-files/SCO/preinstall"}, {"status": "removed", "deletions": 25, "additions": 0, "changes": 25, "filename": "support-files/SCO/preremove"}, {"status": "changed", "deletions": 0, "additions": 0, "changes": 0, "filename": "support-files/SCO/prototype.ini"}], "stats": {"deletions": 3239, "additions": 3296, "total": 6535}, "commit": {"date": "2010-12-28T23:47:05Z", "authorId": "", "author": "Kent Boortz"}}