{"repo": "git", "files": [{"status": "modified", "deletions": 4, "additions": 4, "changes": 8, "filename": "INSTALL"}, {"status": "modified", "deletions": 1, "additions": 1, "changes": 2, "filename": "contrib/examples/git-svnimport.perl"}, {"status": "modified", "deletions": 1, "additions": 2, "changes": 3, "filename": "contrib/fast-import/import-directories.perl"}, {"status": "modified", "deletions": 1, "additions": 3, "changes": 4, "filename": "git-add--interactive.perl"}, {"status": "modified", "deletions": 1, "additions": 2, "changes": 3, "filename": "git-archimport.perl"}, {"status": "modified", "deletions": 1, "additions": 3, "changes": 4, "filename": "git-cvsexportcommit.perl"}, {"status": "modified", "deletions": 1, "additions": 2, "changes": 3, "filename": "git-cvsimport.perl"}, {"status": "modified", "deletions": 0, "additions": 1, "changes": 1, "filename": "git-cvsserver.perl"}, {"status": "modified", "deletions": 0, "additions": 1, "changes": 1, "filename": "git-difftool.perl"}, {"status": "modified", "deletions": 1, "additions": 1, "changes": 2, "filename": "git-relink.perl"}, {"status": "modified", "deletions": 1, "additions": 2, "changes": 3, "filename": "git-send-email.perl"}, {"status": "modified", "deletions": 0, "additions": 1, "changes": 1, "filename": "git-svn.perl"}, {"status": "modified", "deletions": 0, "additions": 1, "changes": 1, "filename": "gitweb/gitweb.perl"}, {"status": "modified", "deletions": 0, "additions": 1, "changes": 1, "filename": "perl/Git.pm"}, {"status": "modified", "deletions": 0, "additions": 1, "changes": 1, "filename": "t/t7006/test-terminal.perl"}, {"status": "modified", "deletions": 1, "additions": 1, "changes": 2, "filename": "t/t9700/test.pl"}], "stats": {"deletions": 13, "additions": 27, "total": 40}, "commit": {"date": "2010-12-09T18:35:21Z", "authorId": "gitster", "author": "Junio C Hamano"}}