{"repo": "finagle", "files": [{"status": "modified", "deletions": 1, "additions": 1, "changes": 2, "filename": "project/build.properties"}, {"status": "modified", "deletions": 35, "additions": 3, "changes": 38, "filename": "project/build/Project.scala"}, {"status": "removed", "deletions": 6, "additions": 0, "changes": 6, "filename": "project/plugins/Plugins.scala"}, {"status": "added", "deletions": 0, "additions": 711, "changes": 711, "filename": "src/test/java/com/twitter/silly/Silly.java"}], "stats": {"deletions": 42, "additions": 715, "total": 757}, "commit": {"date": "2010-10-21T00:09:41Z", "authorId": "", "author": "Nick Kallen"}}