{"repo": "flockdb-client", "files": [{"status": "modified", "deletions": 1, "additions": 1, "changes": 2, "filename": "lib/flock/client.rb"}, {"status": "modified", "deletions": 1, "additions": 8, "changes": 9, "filename": "lib/flock/mock_service.rb"}, {"status": "modified", "deletions": 1, "additions": 1, "changes": 2, "filename": "lib/flock/operations/execute_operation.rb"}, {"status": "modified", "deletions": 0, "additions": 5, "changes": 5, "filename": "lib/flock/operations/execute_operations.rb"}, {"status": "modified", "deletions": 2, "additions": 4, "changes": 6, "filename": "lib/flock/operations/query_term.rb"}, {"status": "modified", "deletions": 1, "additions": 6, "changes": 7, "filename": "lib/flock/operations/simple_operation.rb"}, {"status": "modified", "deletions": 1, "additions": 8, "changes": 9, "filename": "spec/flock_spec.rb"}], "stats": {"deletions": 7, "additions": 33, "total": 40}, "commit": {"date": "2010-05-06T18:23:25Z", "authorId": "kmonkeyjam", "author": "Tina Huang"}}