{"repo": "webrat", "files": [{"status": "modified", "deletions": 9, "additions": 7, "changes": 16, "filename": "Rakefile"}, {"status": "modified", "deletions": 0, "additions": 1, "changes": 1, "filename": "spec/integration/mechanize/spec/spec_helper.rb"}, {"status": "modified", "deletions": 0, "additions": 2, "changes": 2, "filename": "spec/integration/merb/spec/spec_helper.rb"}, {"status": "modified", "deletions": 0, "additions": 1, "changes": 1, "filename": "spec/integration/rack/test/webrat_rack_test.rb"}, {"status": "modified", "deletions": 0, "additions": 1, "changes": 1, "filename": "spec/integration/sinatra/test/classic_app_test.rb"}], "stats": {"deletions": 9, "additions": 12, "total": 21}, "commit": {"date": "2010-04-13T02:30:56Z", "authorId": "djanowski", "author": "Damian Janowski"}}