{"repo": "mysql", "files": [{"status": "modified", "deletions": 7, "additions": 3, "changes": 10, "filename": "client/mysql.cc"}, {"status": "modified", "deletions": 1, "additions": 4, "changes": 5, "filename": "client/mysql_upgrade.c"}, {"status": "modified", "deletions": 4, "additions": 3, "changes": 7, "filename": "client/mysqladmin.cc"}, {"status": "modified", "deletions": 6, "additions": 3, "changes": 9, "filename": "client/mysqlcheck.c"}, {"status": "modified", "deletions": 2, "additions": 3, "changes": 5, "filename": "client/mysqldump.c"}, {"status": "modified", "deletions": 10, "additions": 5, "changes": 15, "filename": "client/mysqlimport.c"}, {"status": "modified", "deletions": 3, "additions": 3, "changes": 6, "filename": "client/mysqlshow.c"}, {"status": "modified", "deletions": 9, "additions": 3, "changes": 12, "filename": "client/mysqltest.cc"}, {"status": "modified", "deletions": 23, "additions": 8, "changes": 31, "filename": "sql/gen_lex_hash.cc"}, {"status": "modified", "deletions": 7, "additions": 4, "changes": 11, "filename": "sql/mysqld.cc"}, {"status": "modified", "deletions": 2, "additions": 2, "changes": 4, "filename": "sql/protocol.cc"}, {"status": "modified", "deletions": 0, "additions": 7, "changes": 7, "filename": "storage/innodb_plugin/ChangeLog"}, {"status": "modified", "deletions": 1, "additions": 5, "changes": 6, "filename": "storage/innodb_plugin/buf/buf0buf.c"}, {"status": "modified", "deletions": 0, "additions": 170, "changes": 170, "filename": "storage/innodb_plugin/buf/buf0rea.c"}, {"status": "modified", "deletions": 0, "additions": 8, "changes": 8, "filename": "storage/innodb_plugin/handler/ha_innodb.cc"}, {"status": "modified", "deletions": 0, "additions": 14, "changes": 14, "filename": "storage/innodb_plugin/include/buf0buf.h"}, {"status": "modified", "deletions": 6, "additions": 22, "changes": 28, "filename": "storage/innodb_plugin/include/buf0buf.ic"}, {"status": "modified", "deletions": 0, "additions": 2, "changes": 2, "filename": "storage/innodb_plugin/include/srv0srv.h"}, {"status": "modified", "deletions": 0, "additions": 4, "changes": 4, "filename": "storage/innodb_plugin/srv/srv0srv.c"}], "stats": {"deletions": 81, "additions": 273, "total": 354}, "commit": {"date": "2011-07-22T08:21:39Z", "authorId": "bjornmu", "author": "Bjorn Munch"}}