{"repo": "pig", "files": [{"status": "modified", "deletions": 0, "additions": 2, "changes": 2, "filename": "CHANGES.txt"}, {"status": "modified", "deletions": 2, "additions": 18, "changes": 20, "filename": "src/org/apache/pig/backend/hadoop/executionengine/physicalLayer/expressionOperators/POUserFunc.java"}, {"status": "modified", "deletions": 1, "additions": 1, "changes": 2, "filename": "src/org/apache/pig/backend/hadoop/executionengine/physicalLayer/relationalOperators/POForEach.java"}, {"status": "modified", "deletions": 0, "additions": 65, "changes": 65, "filename": "test/org/apache/pig/test/TestAccumulator.java"}], "stats": {"deletions": 3, "additions": 86, "total": 89}, "commit": {"date": "2011-04-08T19:01:53Z", "authorId": "", "author": "Thejas Madhavan Nair"}}