{"repo": "flockdb", "files": [{"status": "modified", "deletions": 25, "additions": 9, "changes": 34, "filename": "config/development.scala"}, {"status": "modified", "deletions": 25, "additions": 9, "changes": 34, "filename": "config/production.scala"}, {"status": "modified", "deletions": 2, "additions": 2, "changes": 4, "filename": "project/build.properties"}, {"status": "modified", "deletions": 3, "additions": 5, "changes": 8, "filename": "project/build/FlockDBProject.scala"}, {"status": "modified", "deletions": 2, "additions": 3, "changes": 5, "filename": "project/plugins/Plugins.scala"}, {"status": "added", "deletions": 0, "additions": 4, "changes": 4, "filename": "project/release.properties"}], "stats": {"deletions": 57, "additions": 32, "total": 89}, "commit": {"date": "2011-05-25T00:46:08Z", "authorId": "", "author": "eaceaser"}}