{"repo": "thrift_client", "files": [{"status": "modified", "deletions": 0, "additions": 1, "changes": 1, "filename": "Manifest"}, {"status": "modified", "deletions": 1, "additions": 1, "changes": 2, "filename": "lib/thrift_client.rb"}, {"status": "modified", "deletions": 7, "additions": 6, "changes": 13, "filename": "lib/thrift_client/abstract_thrift_client.rb"}, {"status": "modified", "deletions": 13, "additions": 58, "changes": 71, "filename": "lib/thrift_client/server.rb"}], "stats": {"deletions": 21, "additions": 66, "total": 87}, "commit": {"date": "2012-09-10T21:55:29Z", "authorId": "", "author": "Brandon Mitchell"}}