{"repo": "scalding", "files": [{"status": "modified", "deletions": 0, "additions": 1, "changes": 1, "filename": "src/main/scala/com/twitter/scalding/serialization/KryoHadoop.scala"}, {"status": "modified", "deletions": 0, "additions": 16, "changes": 16, "filename": "src/main/scala/com/twitter/scalding/serialization/KryoSerializers.scala"}, {"status": "modified", "deletions": 0, "additions": 1, "changes": 1, "filename": "src/test/scala/com/twitter/scalding/KryoTest.scala"}], "stats": {"deletions": 0, "additions": 18, "total": 18}, "commit": {"date": "2012-07-18T07:07:55Z", "authorId": "johnynek", "author": "Oscar Boykin"}}