{"repo": "pycascading", "files": [{"status": "modified", "deletions": 2, "additions": 3, "changes": 5, "filename": "examples/joins.py"}, {"status": "modified", "deletions": 2, "additions": 1, "changes": 3, "filename": "examples/map_types.py"}, {"status": "removed", "deletions": 73, "additions": 0, "changes": 73, "filename": "examples/wc.py"}, {"status": "modified", "deletions": 4, "additions": 4, "changes": 8, "filename": "python/pycascading/operators.py"}], "stats": {"deletions": 81, "additions": 8, "total": 89}, "commit": {"date": "2012-04-09T06:26:56Z", "authorId": "", "author": "Gabor Szabo"}}